mproto/__init__.py
mproto/defaults.py
mproto/proto.py
mproto-0.0.2.dist-info/LICENSE
mproto-0.0.2.dist-info/METADATA
mproto-0.0.2.dist-info/WHEEL
mproto-0.0.2.dist-info/top_level.txt
mproto-0.0.2.dist-info/RECORD
