Metadata-Version: 2.1
Name: mproto
Version: 0.0.2
Summary: Make custom protocols
Home-page: https://github.com/ninjamar/mproto
Author: ninjamar
Author-email: author@example.com
License: UNKNOWN
Project-URL: Bug Tracker, https://github.com/ninjamar/mproto/issues
Platform: UNKNOWN
Classifier: Programming Language :: Python :: 3
Classifier: License :: OSI Approved :: MIT License
Classifier: Operating System :: OS Independent
Requires-Python: >=3.7
